raveberry_visualization/__init__.py
raveberry_visualization/raveberry_visualization.cpython-310-x86_64-linux-gnu.so
raveberry_visualization/images/raveberry.png
raveberry_visualization/shaders/Circle/background.fs
raveberry_visualization/shaders/Circle/foreground.fs
raveberry_visualization/shaders/Circle/particle.fs
raveberry_visualization/shaders/Circle/particle.vs
raveberry_visualization/shaders/Circle/quad.vs
raveberry_visualization/shaders/SnowyCircle/background.fs
raveberry_visualization/shaders/SnowyCircle/foreground.fs
raveberry_visualization/shaders/SnowyCircle/particle.fs
raveberry_visualization/shaders/SnowyCircle/particle.vs
raveberry_visualization/shaders/SnowyCircle/quad.vs
raveberry_visualization-0.1.0.dist-info/AUTHORS
raveberry_visualization-0.1.0.dist-info/LICENSE
raveberry_visualization-0.1.0.dist-info/METADATA
raveberry_visualization-0.1.0.dist-info/WHEEL
raveberry_visualization-0.1.0.dist-info/top_level.txt
raveberry_visualization-0.1.0.dist-info/RECORD
