Metadata-Version: 2.1
Name: raveberry-visualization
Version: 0.1.0
Summary: TODO
Home-page: https://github.com/raveberry/visualization
Author: Jonathan Hacker
Author-email: raveberry@jhacker.de
License: UNKNOWN
Platform: UNKNOWN
Classifier: Development Status :: 4 - Beta
Classifier: License :: OSI Approved :: GNU Lesser General Public License v3 (LGPLv3)
Classifier: Programming Language :: Python :: 3
Requires-Python: >=3.8
